flask_djangofy/.DS_Store
flask_djangofy/__init__.py
flask_djangofy/__main__.py
flask_djangofy/apps/__init__.py
flask_djangofy/apps/config.py
flask_djangofy/apps/registry.py
flask_djangofy/conf/__init__.py
flask_djangofy/conf/global_settings.py
flask_djangofy/conf/app_template/__init__.py-tpl
flask_djangofy/conf/app_template/apps.py-tpl
flask_djangofy/conf/app_template/urls.py-tpl
flask_djangofy/conf/app_template/views.py-tpl
flask_djangofy/conf/project_template/manage.py-tpl
flask_djangofy/conf/project_template/project_name/__init__.py-tpl
flask_djangofy/conf/project_template/project_name/settings.py-tpl
flask_djangofy/conf/project_template/project_name/urls.py-tpl
flask_djangofy/conf/project_template/project_name/wsgi.py-tpl
flask_djangofy/core/__init__.py
flask_djangofy/core/exceptions.py
flask_djangofy/core/runner.py
flask_djangofy/core/wsgi.py
flask_djangofy/core/management/__init__.py
flask_djangofy/core/management/base.py
flask_djangofy/core/management/color.py
flask_djangofy/core/management/templates.py
flask_djangofy/core/management/utils.py
flask_djangofy/core/management/commands/__init__.py
flask_djangofy/core/management/commands/runserver.py
flask_djangofy/core/management/commands/startapp.py
flask_djangofy/core/management/commands/startproject.py
flask_djangofy/initializers/__init__.py
flask_djangofy/initializers/base.py
flask_djangofy/initializers/routes.py
flask_djangofy/templates/default_urlconf.html
flask_djangofy/urls/__init__.py
flask_djangofy/urls/include.py
flask_djangofy/urls/path.py
flask_djangofy/utils/__init__.py
flask_djangofy/utils/archive.py
flask_djangofy/utils/crypto.py
flask_djangofy/utils/encoding.py
flask_djangofy/utils/functional.py
flask_djangofy/utils/import_util.py
flask_djangofy/utils/module_loading.py
flask_djangofy/utils/regex_helper.py
flask_djangofy/utils/termcolors.py
flask_djangofy/utils/versions.py
flask_djangofy/views/__init__.py
flask_djangofy/views/base.py
flask_djangofy/views/generics.py
flask_djangofy-1.0.dist-info/LICENSE.txt
flask_djangofy-1.0.dist-info/METADATA
flask_djangofy-1.0.dist-info/WHEEL
flask_djangofy-1.0.dist-info/entry_points.txt
flask_djangofy-1.0.dist-info/top_level.txt
flask_djangofy-1.0.dist-info/RECORD
